sad2xs/__init__.py
sad2xs/_globals.py
sad2xs/config.py
sad2xs/helpers.py
sad2xs/main.py
sad2xs/types.py
sad2xs/converter/_001_parser.py
sad2xs/converter/_002_element_exclusion.py
sad2xs/converter/_003_expression_converter.py
sad2xs/converter/_004_element_converter.py
sad2xs/converter/_005_line_converter.py
sad2xs/converter/_006_solenoid_converter.py
sad2xs/converter/_007_harmonic_rf.py
sad2xs/converter/_008_reversals.py
sad2xs/converter/_009_offset_markers.py
sad2xs/converter/_010_write_lattice.py
sad2xs/converter/_011_write_optics.py
sad2xs/converter/__init__.py
sad2xs/output_writer/_000_helpers.py
sad2xs/output_writer/_001_drift.py
sad2xs/output_writer/_002_bend.py
sad2xs/output_writer/_003_corr.py
sad2xs/output_writer/_004_quad.py
sad2xs/output_writer/_005_sext.py
sad2xs/output_writer/_006_oct.py
sad2xs/output_writer/_007_mult.py
sad2xs/output_writer/_008_sol.py
sad2xs/output_writer/_009_cavity.py
sad2xs/output_writer/_010_refshift.py
sad2xs/output_writer/_011_aperture.py
sad2xs/output_writer/_011_marker.py
sad2xs/output_writer/_012_line.py
sad2xs/output_writer/_012_marker.py
sad2xs/output_writer/_013_line.py
sad2xs/output_writer/_013_model.py
sad2xs/output_writer/_014_model.py
sad2xs/output_writer/_014_offset_markers.py
sad2xs/output_writer/_015_offset_markers.py
sad2xs/output_writer/__init__.py
sad2xs/sad_helpers/__init__.py
sad2xs/sad_helpers/chromaticity.py
sad2xs/sad_helpers/emit.py
sad2xs/sad_helpers/rebuild_lattice.py
sad2xs/sad_helpers/survey.py
sad2xs/sad_helpers/track.py
sad2xs/sad_helpers/transfer_matrix.py
sad2xs/sad_helpers/twiss.py
sad2xs-0.2.0.dist-info/licenses/LICENSE
sad2xs-0.2.0.dist-info/METADATA
sad2xs-0.2.0.dist-info/WHEEL
sad2xs-0.2.0.dist-info/top_level.txt
sad2xs-0.2.0.dist-info/RECORD
