Metadata-Version: 2.4
Name: sad2xs
Version: 0.2.0
Summary: Conversion of SAD lattices to Xtrack format
Home-page: https://github.com/JPTS2/SAD2XS
Download-URL: https://pypi.python.org/pypi/sad2xs
Author: J. Salvesen
Author-email: john.salvesen@cern.ch
License: Apache 2.0
Project-URL: Bug Tracker, https://github.com/JPTS2/SAD2XS/issues
Project-URL: Documentation, https://github.com/JPTS2/SAD2XS/blob/main/README.md
Project-URL: Source Code, https://github.com/JPTS2/SAD2XS
License-File: LICENSE
Requires-Dist: numpy>=1.0
Requires-Dist: xtrack>=0.92
Dynamic: author
Dynamic: author-email
Dynamic: description
Dynamic: description-content-type
Dynamic: download-url
Dynamic: home-page
Dynamic: license
Dynamic: license-file
Dynamic: project-url
Dynamic: requires-dist
Dynamic: summary
